odoo8_addon_mail_attach_existing_attachment-8.0.1.0.0.99.dev14-py2.7-nspkg.pth
odoo8_addon_mail_attach_existing_attachment-8.0.1.0.0.99.dev14.dist-info/METADATA
odoo8_addon_mail_attach_existing_attachment-8.0.1.0.0.99.dev14.dist-info/RECORD
odoo8_addon_mail_attach_existing_attachment-8.0.1.0.0.99.dev14.dist-info/WHEEL
odoo8_addon_mail_attach_existing_attachment-8.0.1.0.0.99.dev14.dist-info/namespace_packages.txt
odoo8_addon_mail_attach_existing_attachment-8.0.1.0.0.99.dev14.dist-info/top_level.txt
odoo_addons/mail_attach_existing_attachment/README.rst
odoo_addons/mail_attach_existing_attachment/__init__.py
odoo_addons/mail_attach_existing_attachment/__openerp__.py
odoo_addons/mail_attach_existing_attachment/i18n/ca.po
odoo_addons/mail_attach_existing_attachment/i18n/de.po
odoo_addons/mail_attach_existing_attachment/i18n/el_GR.po
odoo_addons/mail_attach_existing_attachment/i18n/es.po
odoo_addons/mail_attach_existing_attachment/i18n/es_CO.po
odoo_addons/mail_attach_existing_attachment/i18n/fr.po
odoo_addons/mail_attach_existing_attachment/i18n/mail_attach_existing_attachment.pot
odoo_addons/mail_attach_existing_attachment/i18n/pt_BR.po
odoo_addons/mail_attach_existing_attachment/i18n/sl.po
odoo_addons/mail_attach_existing_attachment/i18n/tr.po
odoo_addons/mail_attach_existing_attachment/static/description/attachment.png
odoo_addons/mail_attach_existing_attachment/static/description/ex_mail_compose_message.png
odoo_addons/mail_attach_existing_attachment/static/description/icon.png
odoo_addons/mail_attach_existing_attachment/tests/__init__.py
odoo_addons/mail_attach_existing_attachment/tests/test_mail_attach_existing_attachment.py
odoo_addons/mail_attach_existing_attachment/wizard/__init__.py
odoo_addons/mail_attach_existing_attachment/wizard/mail_compose_message.py
odoo_addons/mail_attach_existing_attachment/wizard/mail_compose_message_view.xml
